README.txt
setup.py
docs/HISTORY.txt
docs/LICENSE.GPL
docs/LICENSE.txt
qi/__init__.py
qi.xmpp.admin.egg-info/PKG-INFO
qi.xmpp.admin.egg-info/SOURCES.txt
qi.xmpp.admin.egg-info/dependency_links.txt
qi.xmpp.admin.egg-info/entry_points.txt
qi.xmpp.admin.egg-info/namespace_packages.txt
qi.xmpp.admin.egg-info/not-zip-safe
qi.xmpp.admin.egg-info/paster_plugins.txt
qi.xmpp.admin.egg-info/requires.txt
qi.xmpp.admin.egg-info/top_level.txt
qi/xmpp/__init__.py
qi/xmpp/admin/__init__.py
qi/xmpp/admin/admin.py