Metadata-Version: 1.0
Name: qi.xmpp.admin
Version: 0.1
Summary: An xmpp client based on qi.xmpp.client supporting XEP-0133
Home-page: http://chatblox.com
Author: G. Gozadinos
Author-email: ggozad@qiweb.net
License: GPL
Keywords: xmpp admin jabber twisted
Platform: UNKNOWN
Classifier: Programming Language :: Python
Classifier: Topic :: Software Development :: Libraries :: Python Modules
